setup.py
EnrichPy.egg-info/PKG-INFO
EnrichPy.egg-info/SOURCES.txt
EnrichPy.egg-info/dependency_links.txt
EnrichPy.egg-info/requires.txt
EnrichPy.egg-info/top_level.txt
enrichpy/__init__.py
enrichpy/delay.py
enrichpy/enrichment.py
enrichpy/initialmassfunction.py
enrichpy/lifetime.py
enrichpy/padconvolve.py
enrichpy/yields.py