Metadata-Version: 1.0
Name: EnrichPy
Version: 0.1.002
Summary: a package of routines related to chemical enrichment
Home-page: UNKNOWN
Author: Roban Hultman Kramer
Author-email: robanhk@gmail.com
License: MIT
Platform: UNKNOWN
Classifier: License :: OSI Approved :: MIT License
Classifier: Programming Language :: Python
Classifier: Programming Language :: Python :: 2.6
Classifier: Topic :: Scientific/Engineering :: Astronomy
Classifier: Operating System :: OS Independent
